LICENSE.txt
README.md
pyproject.toml
setup.cfg
setup.py
pimms/__init__.py
pimms/calculation.py
pimms/cmdline.py
pimms/immutable.py
pimms/table.py
pimms/util.py
pimms.egg-info/PKG-INFO
pimms.egg-info/SOURCES.txt
pimms.egg-info/dependency_links.txt
pimms.egg-info/requires.txt
pimms.egg-info/top_level.txt
pimms/test/__init__.py
pimms/test/lazy_complex.py
pimms/test/normal_calc.py
pimms/test/tri_calc.py