Metadata-Version: 2.1
Name: pimms
Version: 0.3.23
Summary: Python immutable data structures library
Home-page: https://github.com/noahbenson/pimms/
Author: Noah C. Benson
Author-email: nben@nyu.edu
License: GPLv3
Keywords: persistent immutable functional
License-File: LICENSE.txt
